Metadata-Version: 2.1
Name: scrapy-box
Version: 1.4.2
Summary: 简单易用的scrapy插件盒
Home-page: https://github.com/xlomg/scrapy_box.git
Author: xlomg
Author-email: liu_xianglong@live.com
Maintainer: xlomg
Maintainer-email: liu_xianglong@live.com
License: BSD License
Platform: all
Classifier: Development Status :: 4 - Beta
Classifier: Operating System :: OS Independent
Classifier: Intended Audience :: Developers
Classifier: License :: OSI Approved :: BSD License
Classifier: Programming Language :: Python
Classifier: Programming Language :: Python :: Implementation
Classifier: Programming Language :: Python :: 3
Classifier: Programming Language :: Python :: 3.4
Classifier: Programming Language :: Python :: 3.5
Classifier: Programming Language :: Python :: 3.6
Classifier: Programming Language :: Python :: 3.7
Classifier: Topic :: Software Development :: Libraries
License-File: LICENSE.md
